gadopt/__init__.py
gadopt/approximations.py
gadopt/diagnostics.py
gadopt/equations.py
gadopt/firedrake.pyi
gadopt/free_surface_equation.py
gadopt/inverse.py
gadopt/level_set_tools.py
gadopt/limiter.py
gadopt/momentum_equation.py
gadopt/preconditioners.py
gadopt/scalar_equation.py
gadopt/stokes_integrators.py
gadopt/time_stepper.py
gadopt/transport_solver.py
gadopt/utility.py
gadopt/gplates/__init__.py
gadopt/gplates/gplates.py
gadopt/gplates/gplatesfiles.py
gadopt-4.1.0.dist-info/LICENSE
gadopt-4.1.0.dist-info/METADATA
gadopt-4.1.0.dist-info/WHEEL
gadopt-4.1.0.dist-info/top_level.txt
gadopt-4.1.0.dist-info/RECORD
