Metadata-Version: 2.2
Name: gadopt
Version: 4.1.0
Summary: A computational platform for inverse geodynamics
Author: G-ADOPT Contributors
Classifier: Programming Language :: Python :: 3
Classifier: License :: OSI Approved :: MIT License
Classifier: Operating System :: OS Independent
License-File: LICENSE
Requires-Dist: vtk>=9.0.1
Provides-Extra: demos
Requires-Dist: assess; extra == "demos"
Requires-Dist: gmsh; extra == "demos"
Requires-Dist: imageio; extra == "demos"
Requires-Dist: jupytext; extra == "demos"
Requires-Dist: openpyxl; extra == "demos"
Requires-Dist: pandas; extra == "demos"
Requires-Dist: pyvista; extra == "demos"
Requires-Dist: shapely; extra == "demos"
Provides-Extra: optimisation
Requires-Dist: pyroltrilinos; extra == "optimisation"
